toolx_z/Address_to_lat_long.py
toolx_z/__init__.py
toolx_z-0.1.dist-info/LICENSE
toolx_z-0.1.dist-info/METADATA
toolx_z-0.1.dist-info/WHEEL
toolx_z-0.1.dist-info/entry_points.txt
toolx_z-0.1.dist-info/top_level.txt
toolx_z-0.1.dist-info/RECORD
